backend1/auth/auth_bearer.py
backend1/auth/auth_handler.py
backend1/db/database.py
backend1/db/schemas.py
backend1/main.py
backend1/models/users.py
backend1/operations/users.py
backend1/routers/table.py
backend1/routers/test.py
backend1/routers/users.py
backend1/utils/utilities.py
backend1-1.0.15.dist-info/METADATA
backend1-1.0.15.dist-info/WHEEL
backend1-1.0.15.dist-info/RECORD
